{"event_time": "2025-11-08T13:50:14.446240Z", "bridge_id": 5, "sensor_type": "tilt", "value": 11.792, "ingest_time": "2025-11-08T13:50:14.446282Z"}
{"event_time": "2025-11-08T13:50:14.446292Z", "bridge_id": 4, "sensor_type": "tilt", "value": 1.011, "ingest_time": "2025-11-08T13:50:14.446298Z"}
{"event_time": "2025-11-08T13:49:50.446313Z", "bridge_id": 3, "sensor_type": "tilt", "value": 6.944, "ingest_time": "2025-11-08T13:50:14.446318Z"}
{"event_time": "2025-11-08T13:49:18.454366Z", "bridge_id": 3, "sensor_type": "tilt", "value": 21.828, "ingest_time": "2025-11-08T13:50:15.454427Z"}
{"event_time": "2025-11-08T13:49:56.454436Z", "bridge_id": 5, "sensor_type": "tilt", "value": 28.027, "ingest_time": "2025-11-08T13:50:15.454443Z"}
{"event_time": "2025-11-08T13:49:22.454482Z", "bridge_id": 2, "sensor_type": "tilt", "value": 4.331, "ingest_time": "2025-11-08T13:50:15.454486Z"}
{"event_time": "2025-11-08T13:49:35.454508Z", "bridge_id": 2, "sensor_type": "tilt", "value": 17.971, "ingest_time": "2025-11-08T13:50:15.454512Z"}
{"event_time": "2025-11-08T13:49:48.462110Z", "bridge_id": 4, "sensor_type": "tilt", "value": 3.317, "ingest_time": "2025-11-08T13:50:16.462603Z"}
{"event_time": "2025-11-08T13:49:41.462630Z", "bridge_id": 3, "sensor_type": "tilt", "value": 9.923, "ingest_time": "2025-11-08T13:50:16.462634Z"}
{"event_time": "2025-11-08T13:49:16.462638Z", "bridge_id": 5, "sensor_type": "tilt", "value": 0.474, "ingest_time": "2025-11-08T13:50:16.462643Z"}
{"event_time": "2025-11-08T13:49:28.466732Z", "bridge_id": 5, "sensor_type": "tilt", "value": 4.86, "ingest_time": "2025-11-08T13:50:17.466736Z"}
{"event_time": "2025-11-08T13:49:46.466740Z", "bridge_id": 1, "sensor_type": "tilt", "value": 14.884, "ingest_time": "2025-11-08T13:50:17.466744Z"}
{"event_time": "2025-11-08T13:49:46.466781Z", "bridge_id": 3, "sensor_type": "tilt", "value": 5.975, "ingest_time": "2025-11-08T13:50:17.466785Z"}
{"event_time": "2025-11-08T13:49:34.470499Z", "bridge_id": 5, "sensor_type": "tilt", "value": 11.44, "ingest_time": "2025-11-08T13:50:18.470506Z"}
{"event_time": "2025-11-08T13:49:43.470518Z", "bridge_id": 3, "sensor_type": "tilt", "value": 17.687, "ingest_time": "2025-11-08T13:50:18.470522Z"}
{"event_time": "2025-11-08T13:49:18.470526Z", "bridge_id": 4, "sensor_type": "tilt", "value": 0.213, "ingest_time": "2025-11-08T13:50:18.470531Z"}
{"event_time": "2025-11-08T13:49:44.470563Z", "bridge_id": 5, "sensor_type": "tilt", "value": 0.728, "ingest_time": "2025-11-08T13:50:18.470567Z"}
{"event_time": "2025-11-08T13:49:43.479789Z", "bridge_id": 1, "sensor_type": "tilt", "value": 26.952, "ingest_time": "2025-11-08T13:50:19.479795Z"}
{"event_time": "2025-11-08T13:49:57.479816Z", "bridge_id": 2, "sensor_type": "tilt", "value": 21.83, "ingest_time": "2025-11-08T13:50:19.479820Z"}
{"event_time": "2025-11-08T13:50:06.479840Z", "bridge_id": 3, "sensor_type": "tilt", "value": 20.339, "ingest_time": "2025-11-08T13:50:19.479844Z"}
{"event_time": "2025-11-08T13:49:25.491829Z", "bridge_id": 3, "sensor_type": "tilt", "value": 13.346, "ingest_time": "2025-11-08T13:50:20.491833Z"}
{"event_time": "2025-11-08T13:49:51.491847Z", "bridge_id": 4, "sensor_type": "tilt", "value": 29.264, "ingest_time": "2025-11-08T13:50:20.491851Z"}
{"event_time": "2025-11-08T13:49:43.491855Z", "bridge_id": 1, "sensor_type": "tilt", "value": 3.667, "ingest_time": "2025-11-08T13:50:20.491859Z"}
{"event_time": "2025-11-08T13:49:54.500578Z", "bridge_id": 2, "sensor_type": "tilt", "value": 14.441, "ingest_time": "2025-11-08T13:50:21.500584Z"}
{"event_time": "2025-11-08T13:50:08.500604Z", "bridge_id": 2, "sensor_type": "tilt", "value": 1.136, "ingest_time": "2025-11-08T13:50:21.500608Z"}
{"event_time": "2025-11-08T13:50:10.500620Z", "bridge_id": 1, "sensor_type": "tilt", "value": 3.115, "ingest_time": "2025-11-08T13:50:21.500624Z"}
{"event_time": "2025-11-08T13:49:59.500639Z", "bridge_id": 1, "sensor_type": "tilt", "value": 9.432, "ingest_time": "2025-11-08T13:50:21.500643Z"}
{"event_time": "2025-11-08T13:49:24.506325Z", "bridge_id": 2, "sensor_type": "tilt", "value": 4.83, "ingest_time": "2025-11-08T13:50:22.506332Z"}
{"event_time": "2025-11-08T13:49:33.506336Z", "bridge_id": 3, "sensor_type": "tilt", "value": 19.356, "ingest_time": "2025-11-08T13:50:22.506341Z"}
{"event_time": "2025-11-08T13:49:33.506345Z", "bridge_id": 1, "sensor_type": "tilt", "value": 2.445, "ingest_time": "2025-11-08T13:50:22.506349Z"}
{"event_time": "2025-11-08T13:49:25.506611Z", "bridge_id": 4, "sensor_type": "tilt", "value": 19.425, "ingest_time": "2025-11-08T13:50:22.506623Z"}
