{"event_time": "2025-11-08T10:22:55.432893Z", "bridge_id": 1, "sensor_type": "tilt", "value": 26.11, "ingest_time": "2025-11-08T10:23:40.432971Z"}
{"event_time": "2025-11-08T10:23:14.432997Z", "bridge_id": 4, "sensor_type": "tilt", "value": 9.83, "ingest_time": "2025-11-08T10:23:40.433019Z"}
{"event_time": "2025-11-08T10:23:02.433088Z", "bridge_id": 5, "sensor_type": "tilt", "value": 17.232, "ingest_time": "2025-11-08T10:23:40.433101Z"}
{"event_time": "2025-11-08T10:23:32.433114Z", "bridge_id": 4, "sensor_type": "tilt", "value": 17.639, "ingest_time": "2025-11-08T10:23:40.433126Z"}
{"event_time": "2025-11-08T10:23:38.433190Z", "bridge_id": 5, "sensor_type": "tilt", "value": 27.064, "ingest_time": "2025-11-08T10:23:40.433202Z"}
{"event_time": "2025-11-08T10:23:24.433214Z", "bridge_id": 1, "sensor_type": "tilt", "value": 3.988, "ingest_time": "2025-11-08T10:23:40.433226Z"}
{"event_time": "2025-11-08T10:22:45.433689Z", "bridge_id": 1, "sensor_type": "tilt", "value": 26.672, "ingest_time": "2025-11-08T10:23:41.433788Z"}
{"event_time": "2025-11-08T10:23:23.433973Z", "bridge_id": 3, "sensor_type": "tilt", "value": 5.409, "ingest_time": "2025-11-08T10:23:41.433989Z"}
{"event_time": "2025-11-08T10:23:00.434040Z", "bridge_id": 2, "sensor_type": "tilt", "value": 19.812, "ingest_time": "2025-11-08T10:23:41.434054Z"}
{"event_time": "2025-11-08T10:22:45.435007Z", "bridge_id": 1, "sensor_type": "tilt", "value": 25.457, "ingest_time": "2025-11-08T10:23:42.435025Z"}
{"event_time": "2025-11-08T10:22:52.435041Z", "bridge_id": 4, "sensor_type": "tilt", "value": 22.584, "ingest_time": "2025-11-08T10:23:42.435059Z"}
{"event_time": "2025-11-08T10:23:24.435422Z", "bridge_id": 1, "sensor_type": "tilt", "value": 12.018, "ingest_time": "2025-11-08T10:23:43.435488Z"}
{"event_time": "2025-11-08T10:23:08.435506Z", "bridge_id": 3, "sensor_type": "tilt", "value": 27.899, "ingest_time": "2025-11-08T10:23:43.435522Z"}
{"event_time": "2025-11-08T10:22:56.435533Z", "bridge_id": 3, "sensor_type": "tilt", "value": 25.866, "ingest_time": "2025-11-08T10:23:43.435545Z"}
{"event_time": "2025-11-08T10:23:04.435556Z", "bridge_id": 3, "sensor_type": "tilt", "value": 23.763, "ingest_time": "2025-11-08T10:23:43.435566Z"}
{"event_time": "2025-11-08T10:23:11.435598Z", "bridge_id": 2, "sensor_type": "tilt", "value": 3.81, "ingest_time": "2025-11-08T10:23:43.435608Z"}
{"event_time": "2025-11-08T10:23:43.435639Z", "bridge_id": 2, "sensor_type": "tilt", "value": 5.919, "ingest_time": "2025-11-08T10:23:43.435650Z"}
{"event_time": "2025-11-08T10:23:37.435680Z", "bridge_id": 3, "sensor_type": "tilt", "value": 19.786, "ingest_time": "2025-11-08T10:23:43.435690Z"}
{"event_time": "2025-11-08T10:23:21.435874Z", "bridge_id": 4, "sensor_type": "tilt", "value": 9.263, "ingest_time": "2025-11-08T10:23:44.435962Z"}
{"event_time": "2025-11-08T10:23:06.436031Z", "bridge_id": 1, "sensor_type": "tilt", "value": 24.863, "ingest_time": "2025-11-08T10:23:44.436050Z"}
{"event_time": "2025-11-08T10:23:14.436185Z", "bridge_id": 1, "sensor_type": "tilt", "value": 26.698, "ingest_time": "2025-11-08T10:23:44.436200Z"}
{"event_time": "2025-11-08T10:23:12.436214Z", "bridge_id": 3, "sensor_type": "tilt", "value": 2.65, "ingest_time": "2025-11-08T10:23:44.436228Z"}
{"event_time": "2025-11-08T10:23:11.437269Z", "bridge_id": 3, "sensor_type": "tilt", "value": 28.775, "ingest_time": "2025-11-08T10:23:45.437295Z"}
{"event_time": "2025-11-08T10:22:47.437569Z", "bridge_id": 2, "sensor_type": "tilt", "value": 3.757, "ingest_time": "2025-11-08T10:23:45.437593Z"}
{"event_time": "2025-11-08T10:23:16.437988Z", "bridge_id": 4, "sensor_type": "tilt", "value": 12.257, "ingest_time": "2025-11-08T10:23:46.438003Z"}
{"event_time": "2025-11-08T10:23:26.438075Z", "bridge_id": 4, "sensor_type": "tilt", "value": 2.261, "ingest_time": "2025-11-08T10:23:46.438084Z"}
{"event_time": "2025-11-08T10:23:28.438093Z", "bridge_id": 1, "sensor_type": "tilt", "value": 28.46, "ingest_time": "2025-11-08T10:23:46.438102Z"}
{"event_time": "2025-11-08T10:23:16.439257Z", "bridge_id": 5, "sensor_type": "tilt", "value": 29.739, "ingest_time": "2025-11-08T10:23:47.439284Z"}
{"event_time": "2025-11-08T10:23:41.440523Z", "bridge_id": 4, "sensor_type": "tilt", "value": 19.501, "ingest_time": "2025-11-08T10:23:48.440630Z"}
{"event_time": "2025-11-08T10:23:13.440664Z", "bridge_id": 1, "sensor_type": "tilt", "value": 2.214, "ingest_time": "2025-11-08T10:23:48.440692Z"}
{"event_time": "2025-11-08T10:23:10.440838Z", "bridge_id": 2, "sensor_type": "tilt", "value": 6.173, "ingest_time": "2025-11-08T10:23:48.440858Z"}
{"event_time": "2025-11-08T10:23:19.440956Z", "bridge_id": 5, "sensor_type": "tilt", "value": 9.04, "ingest_time": "2025-11-08T10:23:48.440978Z"}
{"event_time": "2025-11-08T10:23:02.440997Z", "bridge_id": 4, "sensor_type": "tilt", "value": 0.5, "ingest_time": "2025-11-08T10:23:48.441018Z"}
{"event_time": "2025-11-08T10:23:47.441170Z", "bridge_id": 4, "sensor_type": "tilt", "value": 5.629, "ingest_time": "2025-11-08T10:23:49.441189Z"}
{"event_time": "2025-11-08T10:23:20.441199Z", "bridge_id": 3, "sensor_type": "tilt", "value": 6.912, "ingest_time": "2025-11-08T10:23:49.441201Z"}
{"event_time": "2025-11-08T10:23:37.441205Z", "bridge_id": 4, "sensor_type": "tilt", "value": 18.076, "ingest_time": "2025-11-08T10:23:49.441208Z"}
{"event_time": "2025-11-08T10:23:29.441210Z", "bridge_id": 2, "sensor_type": "tilt", "value": 13.869, "ingest_time": "2025-11-08T10:23:49.441212Z"}
